classification_models_1D/__init__.py
classification_models_1D/__version__.py
classification_models_1D/keras.py
classification_models_1D/models_factory.py
classification_models_1D/tfkeras.py
classification_models_1D/weights.py
classification_models_1D/models/__init__.py
classification_models_1D/models/_common_blocks.py
classification_models_1D/models/densenet.py
classification_models_1D/models/efficientnet.py
classification_models_1D/models/efficientnet_v2.py
classification_models_1D/models/inception_resnet_v2.py
classification_models_1D/models/inception_v3.py
classification_models_1D/models/mobilenet.py
classification_models_1D/models/mobilenet_v2.py
classification_models_1D/models/resnet.py
classification_models_1D/models/resnext.py
classification_models_1D/models/senet.py
classification_models_1D/models/vgg16.py
classification_models_1D/models/vgg19.py
classification_models_1D-1.0.1.dist-info/METADATA
classification_models_1D-1.0.1.dist-info/WHEEL
classification_models_1D-1.0.1.dist-info/top_level.txt
classification_models_1D-1.0.1.dist-info/RECORD
