Metadata-Version: 2.1
Name: classification-models-1D
Version: 1.0.1
Summary: Set of models for classification of 1D data.
Home-page: https://github.com/ZFTurbo/classification_models_1D
Author: Roman Solovyev (ZFTurbo)
Author-email: UNKNOWN
License: UNKNOWN
Platform: UNKNOWN
